haystack_integrations/components/embedders/py.typed
haystack_integrations/components/embedders/fastembed/__init__.py
haystack_integrations/components/embedders/fastembed/fastembed_document_embedder.py
haystack_integrations/components/embedders/fastembed/fastembed_sparse_document_embedder.py
haystack_integrations/components/embedders/fastembed/fastembed_sparse_text_embedder.py
haystack_integrations/components/embedders/fastembed/fastembed_text_embedder.py
haystack_integrations/components/embedders/fastembed/embedding_backend/__init__.py
haystack_integrations/components/embedders/fastembed/embedding_backend/fastembed_backend.py
haystack_integrations/components/rankers/py.typed
haystack_integrations/components/rankers/fastembed/__init__.py
haystack_integrations/components/rankers/fastembed/ranker.py
fastembed_haystack-1.5.0.dist-info/METADATA
fastembed_haystack-1.5.0.dist-info/WHEEL
fastembed_haystack-1.5.0.dist-info/licenses/LICENSE.txt
fastembed_haystack-1.5.0.dist-info/RECORD
