Metadata-Version: 2.4
Name: fastembed-haystack
Version: 1.5.0
Summary: Haystack 2.x component to embed strings and Documents using fastembed embedding model
Project-URL: Source, https://github.com/deepset-ai/haystack-core-integrations
Project-URL: Documentation, https://github.com/deepset-ai/haystack-core-integrations/blob/main/integrations/fastembed/README.md
Project-URL: Issues, https://github.com/deepset-ai/haystack-core-integrations/issues
Author-email: deepset GmbH <info@deepset.ai>
License-Expression: Apache-2.0
License-File: LICENSE.txt
Classifier: Development Status :: 4 - Beta
Classifier: License :: OSI Approved :: Apache Software License
Classifier: Programming Language :: Python
Classifier: Programming Language :: Python :: 3.9
Classifier: Programming Language :: Python :: 3.10
Classifier: Programming Language :: Python :: 3.11
Classifier: Programming Language :: Python :: 3.12
Classifier: Programming Language :: Python :: 3.13
Classifier: Programming Language :: Python :: Implementation :: CPython
Classifier: Programming Language :: Python :: Implementation :: PyPy
Requires-Python: >=3.9
Requires-Dist: fastembed>=0.4.2
Requires-Dist: haystack-ai>=2.0.1
